{
    "Netzbetreiber": "Unknown",
    "Produkte": [
        {
            "Name": "CASA",
            "Beschreibung": "Standard tariff for residential use",
            "Komponenten": [
                {
                    "Name": "Tarif",
                    "Beschreibung": "Price per kWh during summer and winter",
                    "Einheit": "Rp./kWh",
                    "Unterkategorie": "Energie",
                    "Menge": "10.4",
                    "Tariftyp": "Einfachtarif",
                    "Tarifzeiten": "All day"
                },
                {
                    "Name": "Tarif",
                    "Beschreibung": "Price per kWh during summer and winter",
                    "Einheit": "Rp./kWh",
                    "Unterkategorie": "Energie",
                    "Menge": "10.4",
                    "Tariftyp": "Einfachtarif",
                    "Tarifzeiten": "All day"
                }
            ],
            "G端ltigkeit": "Year-round",
            "Verbrauchskategorie": "Residential",
            "Verbrauchstyp": "Haushalt",
            "Netzebene": "Niederspannung",
            "Standardprodukt": "Ja"
        },
        {
            "Name": "COMM",
            "Beschreibung": "Commercial tariff for businesses",
            "Komponenten": [
                {
                    "Name": "Tarif",
                    "Beschreibung": "Price per kWh during summer and winter",
                    "Einheit": "Rp./kWh",
                    "Unterkategorie": "Energie",
                    "Menge": "30.1",
                    "Tariftyp": "Einfachtarif",
                    "Tarifzeiten": "All day"
                },
                {
                    "Name": "Tarif",
                    "Beschreibung": "Price per kWh during summer and winter",
                    "Einheit": "Rp./kWh",
                    "Unterkategorie": "Energie",
                    "Menge": "18.2",
                    "Tariftyp": "Einfachtarif",
                    "Tarifzeiten": "All day"
                }
            ],
            "G端ltigkeit": "Year-round",
            "Verbrauchskategorie": "Commercial",
            "Verbrauchstyp": "Gewerbe & Industrie",
            "Netzebene": "Niederspannung",
            "Standardprodukt": "Nein"
        },
        {
            "Name": "BT 50",
            "Beschreibung": "Tariff for medium-sized businesses",
            "Komponenten": [
                {
                    "Name": "Tarif",
                    "Beschreibung": "Price per kWh during summer and winter",
                    "Einheit": "Rp./kWh",
                    "Unterkategorie": "Energie",
                    "Menge": "30.1",
                    "Tariftyp": "Einfachtarif",
                    "Tarifzeiten": "All day"
                },
                {
                    "Name": "Tarif",
                    "Beschreibung": "Price per kWh during summer and winter",
                    "Einheit": "Rp./kWh",
                    "Unterkategorie": "Energie",
                    "Menge": "18.2",
                    "Tariftyp": "Einfachtarif",
                    "Tarifzeiten": "All day"
                }
            ],
            "G端ltigkeit": "Year-round",
            "Verbrauchskategorie": "Medium Business",
            "Verbrauchstyp": "Gewerbe & Industrie",
            "Netzebene": "Niederspannung",
            "Standardprodukt": "Nein"
        },
        {
            "Name": "MT 600",
            "Beschreibung": "Tariff for large businesses",
            "Komponenten": [
                {
                    "Name": "Tarif",
                    "Beschreibung": "Price per kWh during summer and winter",
                    "Einheit": "Rp./kWh",
                    "Unterkategorie": "Energie",
                    "Menge": "24.3",
                    "Tariftyp": "Einfachtarif",
                    "Tarifzeiten": "All day"
                },
                {
                    "Name": "Tarif",
                    "Beschreibung": "Price per kWh during summer and winter",
                    "Einheit": "Rp./kWh",
                    "Unterkategorie": "Energie",
                    "Menge": "13.9",
                    "Tariftyp": "Einfachtarif",
                    "Tarifzeiten": "All day"
                }
            ],
            "G端ltigkeit": "Year-round",
            "Verbrauchskategorie": "Large Business",
            "Verbrauchstyp": "Gewerbe & Industrie",
            "Netzebene": "Niederspannung",
            "Standardprodukt": "Nein"
        }
    ]
}